seleniumuser/__init__.py
seleniumuser/py.typed
seleniumuser/seleniumuser.py
seleniumuser-1.1.4.dist-info/METADATA
seleniumuser-1.1.4.dist-info/WHEEL
seleniumuser-1.1.4.dist-info/licenses/LICENSE.txt
seleniumuser-1.1.4.dist-info/RECORD
