Metadata-Version: 2.4
Name: seleniumuser
Version: 1.1.4
Summary: Selenium wrapper to streamline usage.
Project-URL: Homepage, https://github.com/matt-manes/seleniumuser
Project-URL: Documentation, https://github.com/matt-manes/seleniumuser/tree/main/docs
Project-URL: Source code, https://github.com/matt-manes/seleniumuser/tree/main/src/seleniumuser
Author: Matt Manes
License-File: LICENSE.txt
Keywords: automation,selenium,webscraping
Classifier: License :: OSI Approved :: MIT License
Classifier: Operating System :: OS Independent
Classifier: Programming Language :: Python :: 3
Requires-Python: >=3.10
Requires-Dist: beautifulsoup4
Requires-Dist: bs4
Requires-Dist: noiftimer
Requires-Dist: selenium==4.5.0
Requires-Dist: voxscribe
Requires-Dist: whosyouragent
